{"owner":"IPMA","country":"PT","data":[{"precipitaProb":"19.0","tMin":"12.8","tMax":"17.8","predWindDir":"N","idWeatherType":2,"classWindSpeed":2,"longitude":"-9.1286","forecastDate":"2020-11-03","classPrecInt":0,"latitude":"38.7660"},{"precipitaProb":"8.0","tMin":"10.3","tMax":"15.0","predWindDir":"N","idWeatherType":3,"classWindSpeed":2,"longitude":"-9.1286","forecastDate":"2020-11-04","classPrecInt":0,"latitude":"38.7660"},{"precipitaProb":"100.0","tMin":"11.8","tMax":"17.7","predWindDir":"SE","idWeatherType":9,"classWindSpeed":2,"longitude":"-9.1286","forecastDate":"2020-11-05","classPrecInt":2,"latitude":"38.7660"},{"precipitaProb":"100.0","tMin":"13.0","tMax":"16.4","predWindDir":"SE","idWeatherType":9,"classWindSpeed":2,"longitude":"-9.1286","forecastDate":"2020-11-06","classPrecInt":2,"latitude":"38.7660"},{"precipitaProb":"100.0","tMin":"13.2","tMax":"17.9","predWindDir":"S","idWeatherType":6,"classWindSpeed":2,"longitude":"-9.1286","forecastDate":"2020-11-07","classPrecInt":2,"latitude":"38.7660"}],"globalIdLocal":1110600,"dataUpdate":"2020-11-03T14:31:04","local":"Lisboa"}